{"updated_at":"2026-04-08T19:45:17.795Z","count":20,"items":[{"title":"The Intoxicating Flavor [v0.12.0] [PixelsLab]","link":"https://f95zone.to/threads/the-intoxicating-flavor-v0-12-0-pixelslab.12818/","threadId":12818,"pubDate":"2026-04-08T19:43:51.000Z","author":"PixelsLab","category":"Games","comments":5665,"imageUrl":"/data/news-images/12818.jpg"},{"title":"Blossom of Pleasure [v0.418] [Bildur]","link":"https://f95zone.to/threads/blossom-of-pleasure-v0-418-bildur.77411/","threadId":77411,"pubDate":"2026-04-08T19:43:45.000Z","author":"Bildur","category":"Games","comments":1601,"imageUrl":"/data/news-images/77411.png"},{"title":"League of Legends Custom NSFW skins","link":"https://f95zone.to/threads/league-of-legends-custom-nsfw-skins.212864/","threadId":212864,"pubDate":"2026-04-08T19:43:43.000Z","author":"Emulated_Goat","category":"Mods","comments":3430,"imageUrl":"/data/news-images/212864.png"},{"title":"Urban Demons: Remake [v0.9.2] [Urban Demons]","link":"https://f95zone.to/threads/urban-demons-remake-v0-9-2-urban-demons.210417/","threadId":210417,"pubDate":"2026-04-08T19:43:41.000Z","author":"BaasB","category":"Games","comments":5513,"imageUrl":"/data/news-images/210417.png"},{"title":"Vulgar Reverie [v0.19a] [Saxonado Studios]","link":"https://f95zone.to/threads/vulgar-reverie-v0-19a-saxonado-studios.200342/","threadId":200342,"pubDate":"2026-04-08T19:43:35.000Z","author":"Saxonado Studios","category":"Games","comments":5916,"imageUrl":"/data/news-images/200342.png"},{"title":"Logan Cure Collection [2026-04-08] [LoganCure]","link":"https://f95zone.to/threads/logan-cure-collection-2026-04-08-logancure.16209/","threadId":16209,"pubDate":"2026-04-08T19:43:31.000Z","author":"ZARDOZ7","category":"Comics & Stills","comments":1022,"imageUrl":"/data/news-images/16209.jpg"},{"title":"Ripples [v0.8.0 Public] [Jestur]","link":"https://f95zone.to/threads/ripples-v0-8-0-public-jestur.56110/","threadId":56110,"pubDate":"2026-04-08T19:43:28.000Z","author":"7767","category":"Games","comments":15664,"imageUrl":null},{"title":"Corruption of Champions II [v0.8.29] [Savin/Salamander Studios]","link":"https://f95zone.to/threads/corruption-of-champions-ii-v0-8-29-savin-salamander-studios.11371/","threadId":11371,"pubDate":"2026-04-08T19:43:27.000Z","author":"TheImage","category":"Games","comments":53011,"imageUrl":null},{"title":"Yes, I Am a Furry [v0.2] [GoonerUnleashed]","link":"https://f95zone.to/threads/yes-i-am-a-furry-v0-2-goonerunleashed.276586/","threadId":276586,"pubDate":"2026-04-08T19:43:14.000Z","author":"GoonerUnleashed","category":"Games","comments":422,"imageUrl":"/data/news-images/276586.gif"},{"title":"Masters of Raana [v0.8.4.10] [GrimDark]","link":"https://f95zone.to/threads/masters-of-raana-v0-8-4-10-grimdark.100207/","threadId":100207,"pubDate":"2026-04-08T19:43:12.000Z","author":"GD-studios","category":"Games","comments":24717,"imageUrl":"/data/news-images/100207.jpg"},{"title":"Toxic Attraction DonSilver #Cuckold 8muses forum","link":"https://f95zone.to/threads/toxic-attraction-donsilver-cuckold-8muses-forum.186283/","threadId":186283,"pubDate":"2026-04-08T19:43:09.000Z","author":"adam adm","category":"General Discussions","comments":5034,"imageUrl":null},{"title":"Her Last Piece [Act 2 v1.1.024] [SpiceMerchants]","link":"https://f95zone.to/threads/her-last-piece-act-2-v1-1-024-spicemerchants.224588/","threadId":224588,"pubDate":"2026-04-08T19:42:57.000Z","author":"lostraven","category":"Games","comments":298,"imageUrl":null},{"title":"LonaRPG [B.0.10.7.5.2] [EccmA417]","link":"https://f95zone.to/threads/lonarpg-b-0-10-7-5-2-eccma417.49993/","threadId":49993,"pubDate":"2026-04-08T19:42:49.000Z","author":"7767","category":"Games","comments":29328,"imageUrl":"/data/news-images/49993.png"},{"title":"Shantianxiaozhi Collection [2023-03-12] [Shantianxiaozhi]","link":"https://f95zone.to/threads/shantianxiaozhi-collection-2023-03-12-shantianxiaozhi.110444/","threadId":110444,"pubDate":"2026-04-08T19:42:47.000Z","author":"sivertop","category":"Animations & Loops","comments":256,"imageUrl":"/data/news-images/110444.gif"},{"title":"Kindred [v0.05] [KindredDev]","link":"https://f95zone.to/threads/kindred-v0-05-kindreddev.290954/","threadId":290954,"pubDate":"2026-04-08T19:42:39.000Z","author":"KindredDev","category":"Games","comments":97,"imageUrl":"/data/news-images/290954.png"},{"title":"Her Desire [S1 RE] [Wack Daddy]","link":"https://f95zone.to/threads/her-desire-s1-re-wack-daddy.137206/","threadId":137206,"pubDate":"2026-04-08T19:42:39.000Z","author":"Wack Daddy","category":"Games","comments":4858,"imageUrl":"/data/news-images/137206.png"},{"title":"A Simple Life with My Unobtrusive Sister [v1.02 rev1] [Countercurrent Tea Party]","link":"https://f95zone.to/threads/a-simple-life-with-my-unobtrusive-sister-v1-02-rev1-countercurrent-tea-party.221086/","threadId":221086,"pubDate":"2026-04-08T19:42:22.000Z","author":"BaasB","category":"Games","comments":5614,"imageUrl":null},{"title":"Falling Undercover: Nox Syndicate [v0.08.0] [Azienda]","link":"https://f95zone.to/threads/falling-undercover-nox-syndicate-v0-08-0-azienda.252031/","threadId":252031,"pubDate":"2026-04-08T19:42:12.000Z","author":"BaasB","category":"Games","comments":3994,"imageUrl":"/data/news-images/252031.png"},{"title":"A House in the Rift [v0.8.09] [Zanith]","link":"https://f95zone.to/threads/a-house-in-the-rift-v0-8-09-zanith.29627/","threadId":29627,"pubDate":"2026-04-08T19:42:11.000Z","author":"ZanithOne","category":"Games","comments":14602,"imageUrl":"/data/news-images/29627.png"},{"title":"Nephilim [v0.6.4] [BuuPlays]","link":"https://f95zone.to/threads/nephilim-v0-6-4-buuplays.143045/","threadId":143045,"pubDate":"2026-04-08T19:42:07.000Z","author":"Jeev","category":"Games","comments":8147,"imageUrl":"/data/news-images/143045.png"}]}