{"updated_at":"2026-04-17T05:15:09.528Z","count":20,"items":[{"title":"Succubus Reborn [v20260330a] [Sda-lab]","link":"https://f95zone.to/threads/succubus-reborn-v20260330a-sda-lab.62028/","threadId":62028,"pubDate":"2026-04-17T05:15:05.000Z","author":"Igneel1","category":"Games","comments":4092,"imageUrl":"/data/news-images/62028.png"},{"title":"Monster Girl Tavern [v0.3.0b] [TwistedScarlett]","link":"https://f95zone.to/threads/monster-girl-tavern-v0-3-0b-twistedscarlett.287406/","threadId":287406,"pubDate":"2026-04-17T05:14:44.000Z","author":"TwistedScarlett60","category":"Games","comments":266,"imageUrl":"/data/news-images/287406.jpg"},{"title":"Love vs Lust: The story of a Gigolo [Final] [Digital Tease]","link":"https://f95zone.to/threads/love-vs-lust-the-story-of-a-gigolo-final-digital-tease.295043/","threadId":295043,"pubDate":"2026-04-17T05:13:47.000Z","author":"BaasB","category":"Games","comments":25,"imageUrl":null},{"title":"Nymphomania Priestess [v0.8g] [TechnoBrake]","link":"https://f95zone.to/threads/nymphomania-priestess-v0-8g-technobrake.44110/","threadId":44110,"pubDate":"2026-04-17T05:13:42.000Z","author":"BabyYoda","category":"Games","comments":26222,"imageUrl":"/data/news-images/44110.png"},{"title":"A Wife and Mother [P2 v0.230a + P1 v0.152] [Lust & Passion]","link":"https://f95zone.to/threads/a-wife-and-mother-p2-v0-230a-p1-v0-152-lust-passion.5944/","threadId":5944,"pubDate":"2026-04-17T05:13:38.000Z","author":"CobraSGT","category":"Games","comments":179120,"imageUrl":"/data/news-images/5944.jpg"},{"title":"Skyrim Patreon mods","link":"https://f95zone.to/threads/skyrim-patreon-mods.23840/","threadId":23840,"pubDate":"2026-04-17T05:13:26.000Z","author":"Deathor","category":"General Discussions","comments":21100,"imageUrl":null},{"title":"Mall Creeps [v0.21c] [Kuga_Maru]","link":"https://f95zone.to/threads/mall-creeps-v0-21c-kuga_maru.134160/","threadId":134160,"pubDate":"2026-04-17T05:13:18.000Z","author":"Regless","category":"Games","comments":1160,"imageUrl":"/data/news-images/134160.png"},{"title":"Nessie collection [2024-10-05] [TheRealVinyl]","link":"https://f95zone.to/threads/nessie-collection-2024-10-05-therealvinyl.156432/","threadId":156432,"pubDate":"2026-04-17T05:12:54.000Z","author":"rf96","category":"Animations & Loops","comments":264,"imageUrl":"/data/news-images/156432.gif"},{"title":"Karlsson's Gambit [v0.8.31 FinalB1] [Grym Gudinna Games]","link":"https://f95zone.to/threads/karlssons-gambit-v0-8-31-finalb1-grym-gudinna-games.50840/","threadId":50840,"pubDate":"2026-04-17T05:12:51.000Z","author":"TessSadist","category":"Games","comments":20669,"imageUrl":"/data/news-images/50840.jpg"},{"title":"Planet Lust [Demo] [Skullgear]","link":"https://f95zone.to/threads/planet-lust-demo-skullgear.245599/","threadId":245599,"pubDate":"2026-04-17T05:12:46.000Z","author":"BaasB","category":"Games","comments":277,"imageUrl":"/data/news-images/245599.png"},{"title":"\"The JOI Archive\" The joi Database Patreon exclusive SiteRip v3.1 [2024-10-14]","link":"https://f95zone.to/threads/the-joi-archive-the-joi-database-patreon-exclusive-siterip-v3-1-2024-10-14.162414/","threadId":162414,"pubDate":"2026-04-17T05:12:37.000Z","author":"Skibbybop","category":"General Discussions","comments":9000,"imageUrl":null},{"title":"Deserted Island Company Trip -Women's Survival Strategy- [v1.05] [Yasaniki]","link":"https://f95zone.to/threads/deserted-island-company-trip-womens-survival-strategy-v1-05-yasaniki.278051/","threadId":278051,"pubDate":"2026-04-17T05:12:15.000Z","author":"SakuraKoi","category":"Games","comments":650,"imageUrl":"/data/news-images/278051.jpg"},{"title":"[Translation Request] The Capable Junior, Aoi-chan! ~Our Life Living Together Has Begun~[RJ01473408][Muneniku Tabetai]","link":"https://f95zone.to/threads/translation-request-the-capable-junior-aoi-chan-our-life-living-together-has-begun-rj01473408-muneniku-tabetai.292731/","threadId":292731,"pubDate":"2026-04-17T05:12:13.000Z","author":"KrokZ09","category":"Request","comments":93,"imageUrl":null},{"title":"MILFs of Sunville [S2 v12.00 Extra] [L7team]","link":"https://f95zone.to/threads/milfs-of-sunville-s2-v12-00-extra-l7team.97989/","threadId":97989,"pubDate":"2026-04-17T05:11:59.000Z","author":"BaasB","category":"Games","comments":7799,"imageUrl":"/data/news-images/97989.png"},{"title":"Temporal Breeder [v0.17] [Cosmic Raccoon]","link":"https://f95zone.to/threads/temporal-breeder-v0-17-cosmic-raccoon.267062/","threadId":267062,"pubDate":"2026-04-17T05:11:20.000Z","author":"Bob69","category":"Games","comments":363,"imageUrl":null},{"title":"Fipetopia [v0.6] [Fipetopia]","link":"https://f95zone.to/threads/fipetopia-v0-6-fipetopia.257574/","threadId":257574,"pubDate":"2026-04-17T05:10:03.000Z","author":"Bob69","category":"Games","comments":513,"imageUrl":"/data/news-images/257574.png"},{"title":"My Time with You [Ch.28] [EoloStudios]","link":"https://f95zone.to/threads/my-time-with-you-ch-28-eolostudios.80371/","threadId":80371,"pubDate":"2026-04-17T05:09:43.000Z","author":"eolostudios","category":"Games","comments":1808,"imageUrl":"/data/news-images/80371.png"},{"title":"Agent17 [v0.26.10] [HEXATAIL]","link":"https://f95zone.to/threads/agent17-v0-26-10-hexatail.70810/","threadId":70810,"pubDate":"2026-04-17T05:08:37.000Z","author":"7767","category":"Games","comments":10739,"imageUrl":"/data/news-images/70810.png"},{"title":"Project X Love Potion Disaster RedXCat MOD [v1.3]","link":"https://f95zone.to/threads/project-x-love-potion-disaster-redxcat-mod-v1-3.270099/","threadId":270099,"pubDate":"2026-04-17T05:08:34.000Z","author":"CatInHeat","category":"Mods","comments":489,"imageUrl":"/data/news-images/270099.png"},{"title":"CelSector [v1.1.1] [YumamiSoft]","link":"https://f95zone.to/threads/celsector-v1-1-1-yumamisoft.283889/","threadId":283889,"pubDate":"2026-04-17T05:08:25.000Z","author":"Bob69","category":"Games","comments":2042,"imageUrl":"/data/news-images/283889.png"}]}