{"updated_at":"2026-04-19T04:45:08.412Z","count":20,"items":[{"title":"[Translation Request] - [Yu-RIS Engine] Kenzen! Hentai Rinjin no Sadame [v1.0/DL version] [CLOCKUP]","link":"https://f95zone.to/threads/translation-request-yu-ris-engine-kenzen-hentai-rinjin-no-sadame-v1-0-dl-version-clockup.227886/","threadId":227886,"pubDate":"2026-04-19T04:44:45.000Z","author":"00ein00","category":"Translation","comments":42,"imageUrl":"/data/news-images/227886.png"},{"title":"From Wife to Wench [Ch.6.5] [ForeverLosing]","link":"https://f95zone.to/threads/from-wife-to-wench-ch-6-5-foreverlosing.256683/","threadId":256683,"pubDate":"2026-04-19T04:44:39.000Z","author":"ForeverLosing","category":"Games","comments":2300,"imageUrl":"/data/news-images/256683.png"},{"title":"Big Brother Ultimate [v0.8] [WhiteSilver]","link":"https://f95zone.to/threads/big-brother-ultimate-v0-8-whitesilver.260017/","threadId":260017,"pubDate":"2026-04-19T04:44:27.000Z","author":"White Silver","category":"Games","comments":1963,"imageUrl":"/data/news-images/260017.png"},{"title":"Lessons in Love [v0.57.0] [Selebus]","link":"https://f95zone.to/threads/lessons-in-love-v0-57-0-selebus.48158/","threadId":48158,"pubDate":"2026-04-19T04:44:27.000Z","author":"7767","category":"Games","comments":64822,"imageUrl":null},{"title":"Star Warrior and Space Girls [v0.6.1] [Typiconart]","link":"https://f95zone.to/threads/star-warrior-and-space-girls-v0-6-1-typiconart.186107/","threadId":186107,"pubDate":"2026-04-19T04:44:25.000Z","author":"Typiconart","category":"Games","comments":292,"imageUrl":"/data/news-images/186107.jpg"},{"title":"Edgefield [v0.2.1] [Undercover Pop Games]","link":"https://f95zone.to/threads/edgefield-v0-2-1-undercover-pop-games.248945/","threadId":248945,"pubDate":"2026-04-19T04:44:09.000Z","author":"BaasB","category":"Games","comments":885,"imageUrl":"/data/news-images/248945.png"},{"title":"Adventuring with Belfast in Another World [v0.8] [Templar Studios]","link":"https://f95zone.to/threads/adventuring-with-belfast-in-another-world-v0-8-templar-studios.228285/","threadId":228285,"pubDate":"2026-04-19T04:44:03.000Z","author":"Templar Studios","category":"Games","comments":551,"imageUrl":"/data/news-images/228285.jpg"},{"title":"[Translation Request] Luna and the Ero Trap Dungeon [RJ01596985] [Urasamusun]","link":"https://f95zone.to/threads/translation-request-luna-and-the-ero-trap-dungeon-rj01596985-urasamusun.293317/","threadId":293317,"pubDate":"2026-04-19T04:43:46.000Z","author":"Unenvied0354","category":"Request","comments":32,"imageUrl":"/data/news-images/293317.jpg"},{"title":"Anthro Heat [v1.3.2 Test] [Edef]","link":"https://f95zone.to/threads/anthro-heat-v1-3-2-test-edef.62348/","threadId":62348,"pubDate":"2026-04-19T04:43:44.000Z","author":"FreakyHD","category":"Games","comments":8232,"imageUrl":"/data/news-images/62348.jpg"},{"title":"Boundaries of Morality [v0.69c] [Novel]","link":"https://f95zone.to/threads/boundaries-of-morality-v0-69c-novel.251609/","threadId":251609,"pubDate":"2026-04-19T04:43:43.000Z","author":"UncleVT","category":"Games","comments":3335,"imageUrl":"/data/news-images/251609.png"},{"title":"Project Hivemind [Symbiotic-Route-v1] [Karatus]","link":"https://f95zone.to/threads/project-hivemind-symbiotic-route-v1-karatus.295009/","threadId":295009,"pubDate":"2026-04-19T04:43:16.000Z","author":"Karatus","category":"Games","comments":135,"imageUrl":"/data/news-images/295009.png"},{"title":"God Tier Academy [v0.17f] [SuckylittleD]","link":"https://f95zone.to/threads/god-tier-academy-v0-17f-suckylittled.229786/","threadId":229786,"pubDate":"2026-04-19T04:43:02.000Z","author":"SuckylittleD","category":"Games","comments":356,"imageUrl":"/data/news-images/229786.png"},{"title":"[Translation Request]Magical Girl Alicia 2 ~The Weakening of the Strongest Magical Girl~ [RJ01604757][Todorokimaru]","link":"https://f95zone.to/threads/translation-request-magical-girl-alicia-2-the-weakening-of-the-strongest-magical-girl-rj01604757-todorokimaru.294390/","threadId":294390,"pubDate":"2026-04-19T04:42:50.000Z","author":"EvenForgottenMyName","category":"Request","comments":3,"imageUrl":"/data/news-images/294390.png"},{"title":"Melowh Collection [2026-04-06] [Melowh]","link":"https://f95zone.to/threads/melowh-collection-2026-04-06-melowh.164041/","threadId":164041,"pubDate":"2026-04-19T04:42:43.000Z","author":"Zemax","category":"Comics & Stills","comments":236,"imageUrl":"/data/news-images/164041.jpg"},{"title":"Affect3D - miro Collection [2025-12-17] [Affect3D/affect3d_miro/affect3dx/miro]","link":"https://f95zone.to/threads/affect3d-miro-collection-2025-12-17-affect3d-affect3d_miro-affect3dx-miro.3414/","threadId":3414,"pubDate":"2026-04-19T04:42:39.000Z","author":"7767","category":"Animations & Loops","comments":1944,"imageUrl":"/data/news-images/3414.gif"},{"title":"Moving to the Freeuse World! [v0.1.1] [Dark Romance Interactive]","link":"https://f95zone.to/threads/moving-to-the-freeuse-world-v0-1-1-dark-romance-interactive.295180/","threadId":295180,"pubDate":"2026-04-19T04:42:25.000Z","author":"BaasB","category":"Games","comments":102,"imageUrl":null},{"title":"LonaRPG [B.0.10.7.5.2] [EccmA417]","link":"https://f95zone.to/threads/lonarpg-b-0-10-7-5-2-eccma417.49993/","threadId":49993,"pubDate":"2026-04-19T04:42:10.000Z","author":"7767","category":"Games","comments":29518,"imageUrl":"/data/news-images/49993.png"},{"title":"Abyss: Ultra Fetish [Alpha Demo] [Kazumatsu]","link":"https://f95zone.to/threads/abyss-ultra-fetish-alpha-demo-kazumatsu.295255/","threadId":295255,"pubDate":"2026-04-19T04:41:56.000Z","author":"Kazumatsu (Jujumatsu)","category":"Games","comments":46,"imageUrl":"/data/news-images/295255.png"},{"title":"My Italian Slut Wife [v0.6] [HornyDogStudio]","link":"https://f95zone.to/threads/my-italian-slut-wife-v0-6-hornydogstudio.225161/","threadId":225161,"pubDate":"2026-04-19T04:41:38.000Z","author":"HornyDogStudio","category":"Games","comments":4407,"imageUrl":null},{"title":"Five Nights at KinksDom [v1.5.6 + v2.5] [FNAK Developper]","link":"https://f95zone.to/threads/five-nights-at-kinksdom-v1-5-6-v2-5-fnak-developper.200338/","threadId":200338,"pubDate":"2026-04-19T04:41:19.000Z","author":"FNAK Developper","category":"Games","comments":685,"imageUrl":"/data/news-images/200338.png"}]}