{"updated_at":"2026-03-14T06:45:10.991Z","count":20,"items":[{"title":"Taffy Tales [S2 Redux Demo] [UberPie]","link":"https://f95zone.to/threads/taffy-tales-s2-redux-demo-uberpie.9861/","threadId":9861,"pubDate":"2026-03-14T06:44:37.000Z","author":"Thrownaway13","category":"Games","comments":38840,"imageUrl":"/data/news-images/9861.jpg"},{"title":"Vivid Days [v0.2] [Loys]","link":"https://f95zone.to/threads/vivid-days-v0-2-loys.20748/","threadId":20748,"pubDate":"2026-03-14T06:44:34.000Z","author":"N7","category":"Games","comments":259,"imageUrl":"/data/news-images/20748.png"},{"title":"The Sunset Fairies [v0.14] [Ethan Krautz]","link":"https://f95zone.to/threads/the-sunset-fairies-v0-14-ethan-krautz.142556/","threadId":142556,"pubDate":"2026-03-14T06:44:12.000Z","author":"EthanKrautz","category":"Games","comments":1124,"imageUrl":null},{"title":"Sorcerer [v1.0.0] [Talothral]","link":"https://f95zone.to/threads/sorcerer-v1-0-0-talothral.58369/","threadId":58369,"pubDate":"2026-03-14T06:44:10.000Z","author":"Talothral","category":"Games","comments":4797,"imageUrl":"/data/news-images/58369.jpg"},{"title":"Seeking Closure [v0.9] [Captain Crystallo]","link":"https://f95zone.to/threads/seeking-closure-v0-9-captain-crystallo.146750/","threadId":146750,"pubDate":"2026-03-14T06:43:54.000Z","author":"Captain Crystallo","category":"Games","comments":1209,"imageUrl":"/data/news-images/146750.jpg"},{"title":"Breast Expansion Games Archive (2021)","link":"https://f95zone.to/threads/breast-expansion-games-archive-2021.79536/","threadId":79536,"pubDate":"2026-03-14T06:43:31.000Z","author":"hibilly","category":"Recommendations & Identification","comments":2725,"imageUrl":null},{"title":"Takei's Journey [v0.35] [Ferrum]","link":"https://f95zone.to/threads/takeis-journey-v0-35-ferrum.82236/","threadId":82236,"pubDate":"2026-03-14T06:43:25.000Z","author":"Ferrumx","category":"Games","comments":2554,"imageUrl":"/data/news-images/82236.png"},{"title":"Liepraag Collection [2025-10-10] [Liepraag]","link":"https://f95zone.to/threads/liepraag-collection-2025-10-10-liepraag.220470/","threadId":220470,"pubDate":"2026-03-14T06:43:24.000Z","author":"Kosumo Aphrodisia","category":"Animations & Loops","comments":150,"imageUrl":null},{"title":"Devoted Wife [v0.54] [LoveStory]","link":"https://f95zone.to/threads/devoted-wife-v0-54-lovestory.131853/","threadId":131853,"pubDate":"2026-03-14T06:43:07.000Z","author":"lovestorygames","category":"Games","comments":3163,"imageUrl":"/data/news-images/131853.png"},{"title":"Sinful Ways of Desire [v0.14 Beta] [MILFzone]","link":"https://f95zone.to/threads/sinful-ways-of-desire-v0-14-beta-milfzone.162238/","threadId":162238,"pubDate":"2026-03-14T06:42:50.000Z","author":"KickStart@1870","category":"Games","comments":988,"imageUrl":"/data/news-images/162238.png"},{"title":"Anryms collection [2024-12-29] [Anryms4c41]","link":"https://f95zone.to/threads/anryms-collection-2024-12-29-anryms4c41.180119/","threadId":180119,"pubDate":"2026-03-14T06:42:29.000Z","author":"rf96","category":"Animations & Loops","comments":443,"imageUrl":"/data/news-images/180119.gif"},{"title":"Shadows of Ambition [Ch.7.1] [AbyssGames]","link":"https://f95zone.to/threads/shadows-of-ambition-ch-7-1-abyssgames.231321/","threadId":231321,"pubDate":"2026-03-14T06:41:39.000Z","author":"7767","category":"Games","comments":3790,"imageUrl":"/data/news-images/231321.png"},{"title":"Masters of Raana [v0.8.4.10] [GrimDark]","link":"https://f95zone.to/threads/masters-of-raana-v0-8-4-10-grimdark.100207/","threadId":100207,"pubDate":"2026-03-14T06:41:08.000Z","author":"GD-studios","category":"Games","comments":24102,"imageUrl":"/data/news-images/100207.jpg"},{"title":"FUTA ON MALE content collection(list)","link":"https://f95zone.to/threads/futa-on-male-content-collection-list.78725/","threadId":78725,"pubDate":"2026-03-14T06:40:55.000Z","author":"Choo-choo","category":"Recommendations & Identification","comments":7435,"imageUrl":null},{"title":"Scattered Divine [v1.0] [ShoebillSoup]","link":"https://f95zone.to/threads/scattered-divine-v1-0-shoebillsoup.287218/","threadId":287218,"pubDate":"2026-03-14T06:40:53.000Z","author":"Æяiк","category":"Games","comments":60,"imageUrl":"/data/news-images/287218.jpeg"},{"title":"Being a DIK [v0.11.1] [DrPinkCake]","link":"https://f95zone.to/threads/being-a-dik-v0-11-1-drpinkcake.25332/","threadId":25332,"pubDate":"2026-03-14T06:40:21.000Z","author":"N7","category":"Games","comments":402633,"imageUrl":"/data/news-images/25332.jpg"},{"title":"Amity Park [v1.1.1] [GZone]","link":"https://f95zone.to/threads/amity-park-v1-1-1-gzone.4262/","threadId":4262,"pubDate":"2026-03-14T06:40:12.000Z","author":"Morah SDG","category":"Games","comments":8081,"imageUrl":"/data/news-images/4262.png"},{"title":"Fractured Veil [Act 3 v3.2] [Xeratios]","link":"https://f95zone.to/threads/fractured-veil-act-3-v3-2-xeratios.270244/","threadId":270244,"pubDate":"2026-03-14T06:40:07.000Z","author":"xeratios","category":"Games","comments":667,"imageUrl":null},{"title":"Corruption of Champions II [v0.8.27] [Savin/Salamander Studios]","link":"https://f95zone.to/threads/corruption-of-champions-ii-v0-8-27-savin-salamander-studios.11371/","threadId":11371,"pubDate":"2026-03-14T06:40:02.000Z","author":"TheImage","category":"Games","comments":52065,"imageUrl":null},{"title":"JuicyNeko Collection [2026-02-27] [Juicyneko/juicyneko1]","link":"https://f95zone.to/threads/juicyneko-collection-2026-02-27-juicyneko-juicyneko1.72041/","threadId":72041,"pubDate":"2026-03-14T06:39:51.000Z","author":"rf96","category":"Animations & Loops","comments":466,"imageUrl":null}]}