{"updated_at":"2026-04-13T11:45:08.463Z","count":20,"items":[{"title":"Power Remake [v0.1.3a] [IronNova1991]","link":"https://f95zone.to/threads/power-remake-v0-1-3a-ironnova1991.294355/","threadId":294355,"pubDate":"2026-04-13T11:44:47.000Z","author":"IronNova1991","category":"Games","comments":114,"imageUrl":"/data/news-images/294355.png"},{"title":"[mmd]kotarou3990","link":"https://f95zone.to/threads/mmd-kotarou3990.259487/","threadId":259487,"pubDate":"2026-04-13T11:44:34.000Z","author":"jibanzhiyuan","category":"General Discussions","comments":21,"imageUrl":null},{"title":"NTR Hunter: Hisako’s Secret [v1.2] [Team18]","link":"https://f95zone.to/threads/ntr-hunter-hisakos-secret-v1-2-team18.267292/","threadId":267292,"pubDate":"2026-04-13T11:44:34.000Z","author":"Bob69","category":"Games","comments":897,"imageUrl":"/data/news-images/267292.jpg"},{"title":"Secrets and Promises [v0.07] [badbod]","link":"https://f95zone.to/threads/secrets-and-promises-v0-07-badbod.259286/","threadId":259286,"pubDate":"2026-04-13T11:44:21.000Z","author":"badbod","category":"Games","comments":2143,"imageUrl":"/data/news-images/259286.jpg"},{"title":"Baking With Chocolate [v0.01 Beta] [Moonbox]","link":"https://f95zone.to/threads/baking-with-chocolate-v0-01-beta-moonbox.289655/","threadId":289655,"pubDate":"2026-04-13T11:44:17.000Z","author":"MoonBox","category":"Games","comments":407,"imageUrl":"/data/news-images/289655.png"},{"title":"happy heart panic","link":"https://f95zone.to/threads/happy-heart-panic.293789/","threadId":293789,"pubDate":"2026-04-13T11:43:55.000Z","author":"mr.buss69","category":"Recommendations & Identification","comments":6,"imageUrl":null},{"title":"Bio-Tech Nurse [v1.04] [tenkas]","link":"https://f95zone.to/threads/bio-tech-nurse-v1-04-tenkas.292487/","threadId":292487,"pubDate":"2026-04-13T11:43:47.000Z","author":"Gameil","category":"Games","comments":219,"imageUrl":"/data/news-images/292487.jpg"},{"title":"Sword Art Online: The Trap of Breath Concealed Magic [verβ5] [Fujino]","link":"https://f95zone.to/threads/sword-art-online-the-trap-of-breath-concealed-magic-verv5-fujino.154352/","threadId":154352,"pubDate":"2026-04-13T11:43:38.000Z","author":"BaasB","category":"Games","comments":51075,"imageUrl":"/data/news-images/154352.jpg"},{"title":"Szyca Collection [2025-04-10] [正在創作]","link":"https://f95zone.to/threads/szyca-collection-2025-04-10.251382/","threadId":251382,"pubDate":"2026-04-13T11:43:11.000Z","author":"Dragon x Hunter","category":"Animations & Loops","comments":91,"imageUrl":"/data/news-images/251382.gif"},{"title":"Being a DIK [v0.11.1] [DrPinkCake]","link":"https://f95zone.to/threads/being-a-dik-v0-11-1-drpinkcake.25332/","threadId":25332,"pubDate":"2026-04-13T11:42:59.000Z","author":"N7","category":"Games","comments":407835,"imageUrl":"/data/news-images/25332.jpg"},{"title":"NotAvailableXXX Comic Development","link":"https://f95zone.to/threads/notavailablexxx-comic-development.257158/","threadId":257158,"pubDate":"2026-04-13T11:42:48.000Z","author":"NotAvailableXXX","category":"Programming, Development & Art","comments":673,"imageUrl":null},{"title":"Shadows of Desire [v0.9.0] [Shamantr]","link":"https://f95zone.to/threads/shadows-of-desire-v0-9-0-shamantr.171123/","threadId":171123,"pubDate":"2026-04-13T11:42:31.000Z","author":"7767","category":"Games","comments":7915,"imageUrl":"/data/news-images/171123.png"},{"title":"My Husband's Boss [Ch.3] [SC Stories]","link":"https://f95zone.to/threads/my-husbands-boss-ch-3-sc-stories.241893/","threadId":241893,"pubDate":"2026-04-13T11:42:23.000Z","author":"SC Stories","category":"Games","comments":14666,"imageUrl":"/data/news-images/241893.png"},{"title":"Ratatatat74 Collection [2026-02-03] [Ratatatat74/Mr.Skull/spray and pray]","link":"https://f95zone.to/threads/ratatatat74-collection-2026-02-03-ratatatat74-mr-skull-spray-and-pray.89179/","threadId":89179,"pubDate":"2026-04-13T11:42:02.000Z","author":"Medievalover","category":"Comics & Stills","comments":412,"imageUrl":"/data/news-images/89179.jpg"},{"title":"Life as an Innocent Waitress [v0.4.2 BugFix] [Frisson Studios]","link":"https://f95zone.to/threads/life-as-an-innocent-waitress-v0-4-2-bugfix-frisson-studios.248631/","threadId":248631,"pubDate":"2026-04-13T11:41:52.000Z","author":"Lerd0","category":"Games","comments":3087,"imageUrl":"/data/news-images/248631.png"},{"title":"Lovephobia [v0.85] [Kuviragames]","link":"https://f95zone.to/threads/lovephobia-v0-85-kuviragames.232985/","threadId":232985,"pubDate":"2026-04-13T11:41:20.000Z","author":"Kuviragames","category":"Games","comments":3237,"imageUrl":"/data/news-images/232985.jpg"},{"title":"Milfairy Tales [v.0.7175b] [LeelaK]","link":"https://f95zone.to/threads/milfairy-tales-v-0-7175b-leelak.48600/","threadId":48600,"pubDate":"2026-04-13T11:41:15.000Z","author":"LeelaK","category":"Games","comments":2673,"imageUrl":"/data/news-images/48600.png"},{"title":"Futadom World - Binding Sim [v0.9.9] [F.W.G.B.S.]","link":"https://f95zone.to/threads/futadom-world-binding-sim-v0-9-9-f-w-g-b-s.1780/","threadId":1780,"pubDate":"2026-04-13T11:41:12.000Z","author":"TCMS","category":"Games","comments":7908,"imageUrl":null},{"title":"Maya's Life [v0.1.6] [SleepDage]","link":"https://f95zone.to/threads/mayas-life-v0-1-6-sleepdage.287766/","threadId":287766,"pubDate":"2026-04-13T11:41:10.000Z","author":"Lerd0","category":"Games","comments":100,"imageUrl":"/data/news-images/287766.png"},{"title":"Immoral Stories Rebecca [v1.7.6b] [GGG33]","link":"https://f95zone.to/threads/immoral-stories-rebecca-v1-7-6b-ggg33.97708/","threadId":97708,"pubDate":"2026-04-13T11:40:38.000Z","author":"Powerbabe","category":"Games","comments":2004,"imageUrl":"/data/news-images/97708.png"}]}