{"updated_at":"2026-03-21T05:45:10.817Z","count":20,"items":[{"title":"Nikke goddess of victory (144.8.11)","link":"https://f95zone.to/threads/nikke-goddess-of-victory-144-8-11.276003/","threadId":276003,"pubDate":"2026-03-21T05:44:41.000Z","author":"Minori_uwu","category":"Mods","comments":148,"imageUrl":null},{"title":"Race of Life [Act 2 Ep.4 Fix 4] [Underground Studio]","link":"https://f95zone.to/threads/race-of-life-act-2-ep-4-fix-4-underground-studio.130096/","threadId":130096,"pubDate":"2026-03-21T05:44:38.000Z","author":"UndergroundStudio","category":"Games","comments":10952,"imageUrl":"/data/news-images/130096.png"},{"title":"My New Life: Revamp [v0.98.8] [Beggar of Net]","link":"https://f95zone.to/threads/my-new-life-revamp-v0-98-8-beggar-of-net.30576/","threadId":30576,"pubDate":"2026-03-21T05:43:48.000Z","author":"Pinguino47","category":"Games","comments":45905,"imageUrl":null},{"title":"Brown Dust 2 - BrownDustX mod","link":"https://f95zone.to/threads/brown-dust-2-browndustx-mod.252931/","threadId":252931,"pubDate":"2026-03-21T05:42:59.000Z","author":"nmlss_","category":"Mods","comments":1671,"imageUrl":null},{"title":"Long Road Home [Ep.16] [OBDGames]","link":"https://f95zone.to/threads/long-road-home-ep-16-obdgames.45466/","threadId":45466,"pubDate":"2026-03-21T05:42:41.000Z","author":"Crazygamer43","category":"Games","comments":22260,"imageUrl":"/data/news-images/45466.png"},{"title":"Paradise Succubus / パラダイス・サキュバス","link":"https://f95zone.to/threads/paradise-succubus-paradaisu_sakyubasu.148002/","threadId":148002,"pubDate":"2026-03-21T05:42:40.000Z","author":"AceCyclone","category":"Translation","comments":652,"imageUrl":null},{"title":"Of Birds and Bees [v1.1] [DiscipleOfVirginia]","link":"https://f95zone.to/threads/of-birds-and-bees-v1-1-discipleofvirginia.42860/","threadId":42860,"pubDate":"2026-03-21T05:42:38.000Z","author":"Crazygamer43","category":"Games","comments":2567,"imageUrl":"/data/news-images/42860.gif"},{"title":"The Witch of the End [v1.0] [K.O Workshop]","link":"https://f95zone.to/threads/the-witch-of-the-end-v1-0-k-o-workshop.289968/","threadId":289968,"pubDate":"2026-03-21T05:42:23.000Z","author":"NoodleX2","category":"Games","comments":57,"imageUrl":null},{"title":"Melphias: Azure and Crimson Verge [v1.226] [dorgel]","link":"https://f95zone.to/threads/melphias-azure-and-crimson-verge-v1-226-dorgel.253466/","threadId":253466,"pubDate":"2026-03-21T05:41:52.000Z","author":"dazedanon","category":"Games","comments":817,"imageUrl":null},{"title":"Riboshika Collection [2025-09-23] [リボシカ]","link":"https://f95zone.to/threads/riboshika-collection-2025-09-23-riboshika.263593/","threadId":263593,"pubDate":"2026-03-21T05:41:51.000Z","author":"Kosumo Aphrodisia","category":"Comics & Stills","comments":4,"imageUrl":"/data/news-images/263593.gif"},{"title":"Everything Investigator Girl [Final] [HappyPink]","link":"https://f95zone.to/threads/everything-investigator-girl-final-happypink.3753/","threadId":3753,"pubDate":"2026-03-21T05:40:55.000Z","author":"jande21","category":"Games","comments":179,"imageUrl":"/data/news-images/3753.jpg"},{"title":"Lessons in Love [v0.57.0] [Selebus]","link":"https://f95zone.to/threads/lessons-in-love-v0-57-0-selebus.48158/","threadId":48158,"pubDate":"2026-03-21T05:40:03.000Z","author":"7767","category":"Games","comments":64160,"imageUrl":null},{"title":"Strip Club Wars [v2.11] [Total Fluke Studios]","link":"https://f95zone.to/threads/strip-club-wars-v2-11-total-fluke-studios.187856/","threadId":187856,"pubDate":"2026-03-21T05:39:52.000Z","author":"TotalFluke","category":"Games","comments":7423,"imageUrl":"/data/news-images/187856.jpg"},{"title":"Confession Game [v1.0.1] [Hall of Corruption]","link":"https://f95zone.to/threads/confession-game-v1-0-1-hall-of-corruption.156470/","threadId":156470,"pubDate":"2026-03-21T05:39:03.000Z","author":"dazedanon","category":"Games","comments":592,"imageUrl":null},{"title":"ProjectR [v0.7.0.0] [Team-Apple Pie]","link":"https://f95zone.to/threads/projectr-v0-7-0-0-team-apple-pie.181803/","threadId":181803,"pubDate":"2026-03-21T05:38:52.000Z","author":"Ω Nelo Angelo Ω","category":"Games","comments":4580,"imageUrl":null},{"title":"Skyrim Patreon mods","link":"https://f95zone.to/threads/skyrim-patreon-mods.23840/","threadId":23840,"pubDate":"2026-03-21T05:38:29.000Z","author":"Deathor","category":"General Discussions","comments":20486,"imageUrl":null},{"title":"Eruption Imminent [v0.6.1] [MorriganRae]","link":"https://f95zone.to/threads/eruption-imminent-v0-6-1-morriganrae.160930/","threadId":160930,"pubDate":"2026-03-21T05:38:15.000Z","author":"7767","category":"Games","comments":9450,"imageUrl":"/data/news-images/160930.png"},{"title":"My Naughty Daughter [v5.2.0] [RustyV]","link":"https://f95zone.to/threads/my-naughty-daughter-v5-2-0-rustyv.152233/","threadId":152233,"pubDate":"2026-03-21T05:38:06.000Z","author":"RustyV","category":"Games","comments":1960,"imageUrl":"/data/news-images/152233.jpg"},{"title":"I'm looking for two games","link":"https://f95zone.to/threads/im-looking-for-two-games.291728/","threadId":291728,"pubDate":"2026-03-21T05:37:02.000Z","author":"CjRob","category":"General Discussions","comments":1,"imageUrl":null},{"title":"Harem in Another World [v1.05] [Jong Games]","link":"https://f95zone.to/threads/harem-in-another-world-v1-05-jong-games.135827/","threadId":135827,"pubDate":"2026-03-21T05:36:28.000Z","author":"Jong Games","category":"Games","comments":1689,"imageUrl":"/data/news-images/135827.png"}]}