{"updated_at":"2026-03-29T13:15:11.903Z","count":20,"items":[{"title":"Abyss Awakening [v0.1] [Mata Games]","link":"https://f95zone.to/threads/abyss-awakening-v0-1-mata-games.292804/","threadId":292804,"pubDate":"2026-03-29T13:15:10.000Z","author":"BaasB","category":"Games","comments":1,"imageUrl":null},{"title":"Lunar's Chosen [Ep.2 v0.8 Public] [PTGames]","link":"https://f95zone.to/threads/lunars-chosen-ep-2-v0-8-public-ptgames.28364/","threadId":28364,"pubDate":"2026-03-29T13:15:00.000Z","author":"TheImage","category":"Games","comments":8167,"imageUrl":"/data/news-images/28364.png"},{"title":"Power of Will [v0.086a] [G28]","link":"https://f95zone.to/threads/power-of-will-v0-086a-g28.174500/","threadId":174500,"pubDate":"2026-03-29T13:14:54.000Z","author":"G28Here","category":"Games","comments":932,"imageUrl":"/data/news-images/174500.png"},{"title":"Grandma's House Teil 1-7 &amp; weitere Moonbox Spiele (Deutsche Übersetzung by Spatenklopper)","link":"https://f95zone.to/threads/grandmas-house-teil-1-7-weitere-moonbox-spiele-deutsche-uebersetzung-by-spatenklopper.117906/","threadId":117906,"pubDate":"2026-03-29T13:14:31.000Z","author":"Spatenklopper","category":"Translations Mods","comments":703,"imageUrl":"/data/news-images/117906.jpg"},{"title":"The Daddy Plan [v0.0.9] [ShaddyGames]","link":"https://f95zone.to/threads/the-daddy-plan-v0-0-9-shaddygames.150690/","threadId":150690,"pubDate":"2026-03-29T13:14:29.000Z","author":"ShaddyGames","category":"Games","comments":2029,"imageUrl":null},{"title":"Why Kemono.party is only updating patreon?","link":"https://f95zone.to/threads/why-kemono-party-is-only-updating-patreon.176707/","threadId":176707,"pubDate":"2026-03-29T13:14:15.000Z","author":"Gabriel Drbug","category":"General Discussions","comments":310,"imageUrl":null},{"title":"Netorare God; Netorase Devil [v0.11] [CulturedGamer]","link":"https://f95zone.to/threads/netorare-god-netorase-devil-v0-11-culturedgamer.149486/","threadId":149486,"pubDate":"2026-03-29T13:13:58.000Z","author":"CulturedGamer","category":"Games","comments":1619,"imageUrl":"/data/news-images/149486.jpg"},{"title":"NTR Chat: College Issues [v0.5] [KusoBin]","link":"https://f95zone.to/threads/ntr-chat-college-issues-v0-5-kusobin.270498/","threadId":270498,"pubDate":"2026-03-29T13:13:37.000Z","author":"KusoBin","category":"Games","comments":206,"imageUrl":"/data/news-images/270498.png"},{"title":"Lessons in Love [v0.57.0] [Selebus]","link":"https://f95zone.to/threads/lessons-in-love-v0-57-0-selebus.48158/","threadId":48158,"pubDate":"2026-03-29T13:13:29.000Z","author":"7767","category":"Games","comments":64366,"imageUrl":null},{"title":"Yamada-san is good at cuckolding [v1.01] [PlumSoftware]","link":"https://f95zone.to/threads/yamada-san-is-good-at-cuckolding-v1-01-plumsoftware.292740/","threadId":292740,"pubDate":"2026-03-29T13:13:21.000Z","author":"BreezerTheCat","category":"Games","comments":16,"imageUrl":"/data/news-images/292740.jpg"},{"title":"Sword Art Online: The Trap of Breath Concealed Magic [verβ4] [Fujino]","link":"https://f95zone.to/threads/sword-art-online-the-trap-of-breath-concealed-magic-verv4-fujino.154352/","threadId":154352,"pubDate":"2026-03-29T13:13:08.000Z","author":"BaasB","category":"Games","comments":49861,"imageUrl":"/data/news-images/154352.jpg"},{"title":"Grandma's House [Part 7 v0.100] [Moonbox]","link":"https://f95zone.to/threads/grandmas-house-part-7-v0-100-moonbox.94140/","threadId":94140,"pubDate":"2026-03-29T13:13:07.000Z","author":"MoonBox","category":"Games","comments":45372,"imageUrl":"/data/news-images/94140.jpg"},{"title":"[BepInEx][plugin] Texture Replacer v1.2.0.4","link":"https://f95zone.to/threads/bepinex-plugin-texture-replacer-v1-2-0-4.118422/","threadId":118422,"pubDate":"2026-03-29T13:13:03.000Z","author":"kumarin","category":"Tools & Tutorials","comments":316,"imageUrl":null},{"title":"[DeepL MTL Release]  Incubus Quest [RJ302522] [SweetRaspberry]","link":"https://f95zone.to/threads/deepl-mtl-release-incubus-quest-rj302522-sweetraspberry.90798/","threadId":90798,"pubDate":"2026-03-29T13:12:41.000Z","author":"-Nynx-","category":"Translation","comments":53,"imageUrl":null},{"title":"\"The JOI Archive\" The joi Database Patreon exclusive SiteRip v3.1 [2024-10-14]","link":"https://f95zone.to/threads/the-joi-archive-the-joi-database-patreon-exclusive-siterip-v3-1-2024-10-14.162414/","threadId":162414,"pubDate":"2026-03-29T13:12:39.000Z","author":"Skibbybop","category":"General Discussions","comments":8630,"imageUrl":null},{"title":"Third Crisis [v1.1.0] [Anduo Games]","link":"https://f95zone.to/threads/third-crisis-v1-1-0-anduo-games.9027/","threadId":9027,"pubDate":"2026-03-29T13:12:02.000Z","author":"Vilsa Nara","category":"Games","comments":6011,"imageUrl":"/data/news-images/9027.png"},{"title":"My Wife and I ～Shipwrecked on a Desert Island [Final] [odenslime]","link":"https://f95zone.to/threads/my-wife-and-i-shipwrecked-on-a-desert-island-final-odenslime.165717/","threadId":165717,"pubDate":"2026-03-29T13:12:02.000Z","author":"Vakalo","category":"Games","comments":227,"imageUrl":"/data/news-images/165717.png"},{"title":"Tune in to the Show [P2 Ep.11] [RobertDeadth]","link":"https://f95zone.to/threads/tune-in-to-the-show-p2-ep-11-robertdeadth.108168/","threadId":108168,"pubDate":"2026-03-29T13:11:57.000Z","author":"RobertDeadth","category":"Games","comments":1771,"imageUrl":"/data/news-images/108168.png"},{"title":"Where the Heart Is [EP25] [CheekyGimp]","link":"https://f95zone.to/threads/where-the-heart-is-ep25-cheekygimp.10549/","threadId":10549,"pubDate":"2026-03-29T13:11:55.000Z","author":"UncleVT","category":"Games","comments":37197,"imageUrl":"/data/news-images/10549.png"},{"title":"Chronoromancer [v0.89] [Chronoromancer Studio]","link":"https://f95zone.to/threads/chronoromancer-v0-89-chronoromancer-studio.272335/","threadId":272335,"pubDate":"2026-03-29T13:11:52.000Z","author":"Chronoromancer","category":"Games","comments":364,"imageUrl":"/data/news-images/272335.jpg"}]}