{"updated_at":"2026-04-19T14:40:09.703Z","count":20,"items":[{"title":"Mutto_Studio Videos","link":"https://f95zone.to/threads/mutto_studio-videos.253555/","threadId":253555,"pubDate":"2026-04-19T14:39:54.000Z","author":"JHib123","category":"Recommendations & Identification","comments":123,"imageUrl":null},{"title":"Trials in Tainted Space [v0.9.156] [Fenoxo]","link":"https://f95zone.to/threads/trials-in-tainted-space-v0-9-156-fenoxo.469/","threadId":469,"pubDate":"2026-04-19T14:39:36.000Z","author":"7767","category":"Games","comments":17578,"imageUrl":"/data/news-images/469.jpg"},{"title":"[Translation Request] [RJ224486] 働くアイリがキリ斬りス","link":"https://f95zone.to/threads/translation-request-rj224486-kuairigakiri-risu.48187/","threadId":48187,"pubDate":"2026-04-19T14:39:33.000Z","author":"z0r","category":"Request","comments":100,"imageUrl":"/data/news-images/48187.jpg"},{"title":"Giant Guardians [v0.4.2] [Giant Guardians]","link":"https://f95zone.to/threads/giant-guardians-v0-4-2-giant-guardians.72480/","threadId":72480,"pubDate":"2026-04-19T14:39:31.000Z","author":"BaasB","category":"Games","comments":15294,"imageUrl":null},{"title":"Ms.Denvers [v0.1.2.6] [Pop Toc]","link":"https://f95zone.to/threads/ms-denvers-v0-1-2-6-pop-toc.143472/","threadId":143472,"pubDate":"2026-04-19T14:39:26.000Z","author":"7767","category":"Games","comments":13841,"imageUrl":"/data/news-images/143472.jpg"},{"title":"No nuT iSekai [v0.1] [Chibi Mage]","link":"https://f95zone.to/threads/no-nut-isekai-v0-1-chibi-mage.291604/","threadId":291604,"pubDate":"2026-04-19T14:38:58.000Z","author":"Chibi Mage","category":"Games","comments":78,"imageUrl":"/data/news-images/291604.gif"},{"title":"Life With a Slave  -Teaching Feeling- [v4.0.6 - v2.5.2] [FreakilyCharming]","link":"https://f95zone.to/threads/life-with-a-slave-teaching-feeling-v4-0-6-v2-5-2-freakilycharming.21/","threadId":21,"pubDate":"2026-04-19T14:38:44.000Z","author":"7767","category":"Games","comments":13514,"imageUrl":"/data/news-images/21.png"},{"title":"UNDAWN: Shackles Of Eternity [Ch.1 Fix] [Kind Nightmares]","link":"https://f95zone.to/threads/undawn-shackles-of-eternity-ch-1-fix-kind-nightmares.275045/","threadId":275045,"pubDate":"2026-04-19T14:38:31.000Z","author":"Bob69","category":"Games","comments":877,"imageUrl":"/data/news-images/275045.jpg"},{"title":"My Early Life [Ep.32.01] [CeLaVie Group]","link":"https://f95zone.to/threads/my-early-life-ep-32-01-celavie-group.166790/","threadId":166790,"pubDate":"2026-04-19T14:38:28.000Z","author":"Celaviegroup","category":"Games","comments":4624,"imageUrl":null},{"title":"Adventuring with Belfast in Another World [v0.8] [Templar Studios]","link":"https://f95zone.to/threads/adventuring-with-belfast-in-another-world-v0-8-templar-studios.228285/","threadId":228285,"pubDate":"2026-04-19T14:38:20.000Z","author":"Templar Studios","category":"Games","comments":555,"imageUrl":"/data/news-images/228285.jpg"},{"title":"A Wife and Mother [P2 v0.230a + P1 v0.152] [Lust & Passion]","link":"https://f95zone.to/threads/a-wife-and-mother-p2-v0-230a-p1-v0-152-lust-passion.5944/","threadId":5944,"pubDate":"2026-04-19T14:38:17.000Z","author":"CobraSGT","category":"Games","comments":179249,"imageUrl":"/data/news-images/5944.jpg"},{"title":"Luminary Protocol [v0.51] [Jubs Games]","link":"https://f95zone.to/threads/luminary-protocol-v0-51-jubs-games.261964/","threadId":261964,"pubDate":"2026-04-19T14:37:46.000Z","author":"Jubs!","category":"Games","comments":1104,"imageUrl":"/data/news-images/261964.jpg"},{"title":"Mystery of Magic [v0.2.5p] [Kitty_SFM]","link":"https://f95zone.to/threads/mystery-of-magic-v0-2-5p-kitty_sfm.70118/","threadId":70118,"pubDate":"2026-04-19T14:37:44.000Z","author":"Kitty_SFM(Developer)","category":"Games","comments":481,"imageUrl":"/data/news-images/70118.png"},{"title":"My Femboy Roommate [v1.1 Final] [Nuteku]","link":"https://f95zone.to/threads/my-femboy-roommate-v1-1-final-nuteku.221794/","threadId":221794,"pubDate":"2026-04-19T14:37:41.000Z","author":"7767","category":"Games","comments":739,"imageUrl":"/data/news-images/221794.png"},{"title":"Guys, do you guys have any Femboy game recommendations?","link":"https://f95zone.to/threads/guys-do-you-guys-have-any-femboy-game-recommendations.295399/","threadId":295399,"pubDate":"2026-04-19T14:37:30.000Z","author":"3157516276","category":"General Discussions","comments":1,"imageUrl":null},{"title":"My Husband's Boss [Ch.3] [SC Stories]","link":"https://f95zone.to/threads/my-husbands-boss-ch-3-sc-stories.241893/","threadId":241893,"pubDate":"2026-04-19T14:37:28.000Z","author":"SC Stories","category":"Games","comments":15473,"imageUrl":"/data/news-images/241893.png"},{"title":"A Struggle with Sin [v0.6.2.0b] [Chyos]","link":"https://f95zone.to/threads/a-struggle-with-sin-v0-6-2-0b-chyos.32136/","threadId":32136,"pubDate":"2026-04-19T14:37:17.000Z","author":"Chyos","category":"Games","comments":46446,"imageUrl":null},{"title":"Kemono Party Requests","link":"https://f95zone.to/threads/kemono-party-requests.188349/","threadId":188349,"pubDate":"2026-04-19T14:37:02.000Z","author":"Fire117","category":"General Discussions","comments":4859,"imageUrl":null},{"title":"Harem Hotel [v0.19.1] [Runey]","link":"https://f95zone.to/threads/harem-hotel-v0-19-1-runey.12760/","threadId":12760,"pubDate":"2026-04-19T14:36:51.000Z","author":"xןʞ","category":"Games","comments":51340,"imageUrl":null},{"title":"NTR Sim [v0.3.3.4] [KTRGames]","link":"https://f95zone.to/threads/ntr-sim-v0-3-3-4-ktrgames.290010/","threadId":290010,"pubDate":"2026-04-19T14:36:14.000Z","author":"Kurotori","category":"Games","comments":480,"imageUrl":null}]}