{"updated_at":"2026-04-19T22:00:47.501Z","count":20,"items":[{"title":"Snapshot: Naughty Nightmares [v1.42] [Tiny Secret Games]","link":"https://f95zone.to/threads/snapshot-naughty-nightmares-v1-42-tiny-secret-games.274923/","threadId":274923,"pubDate":"2026-04-19T22:00:41.000Z","author":"Frarexa","category":"Games","comments":63,"imageUrl":"/data/news-images/274923.png"},{"title":"inZOI – Adult Mods","link":"https://f95zone.to/threads/inzoi-adult-mods.251170/","threadId":251170,"pubDate":"2026-04-19T22:00:40.000Z","author":"Dark Lord Nova","category":"General Discussions","comments":106,"imageUrl":null},{"title":"Generic Porn Game 1 - Origination [v0.18] [CreativelyChallengedDeveloper]","link":"https://f95zone.to/threads/generic-porn-game-1-origination-v0-18-creativelychallengeddeveloper.220529/","threadId":220529,"pubDate":"2026-04-19T22:00:38.000Z","author":"Creatively Challenged Dev","category":"Games","comments":730,"imageUrl":null},{"title":"Uni [v0.64.127b] [Hizor Games]","link":"https://f95zone.to/threads/uni-v0-64-127b-hizor-games.15645/","threadId":15645,"pubDate":"2026-04-19T22:00:35.000Z","author":"UncleVT","category":"Games","comments":4559,"imageUrl":"/data/news-images/15645.png"},{"title":"Breast Expansion Games Archive (2021)","link":"https://f95zone.to/threads/breast-expansion-games-archive-2021.79536/","threadId":79536,"pubDate":"2026-04-19T22:00:29.000Z","author":"hibilly","category":"Recommendations & Identification","comments":2827,"imageUrl":null},{"title":"From Wife to Wench [Ch.6.5] [ForeverLosing]","link":"https://f95zone.to/threads/from-wife-to-wench-ch-6-5-foreverlosing.256683/","threadId":256683,"pubDate":"2026-04-19T22:00:24.000Z","author":"ForeverLosing","category":"Games","comments":2304,"imageUrl":"/data/news-images/256683.png"},{"title":"REC [v0.5.0.2] [moondev]","link":"https://f95zone.to/threads/rec-v0-5-0-2-moondev.251935/","threadId":251935,"pubDate":"2026-04-19T21:59:50.000Z","author":"moondev64","category":"Games","comments":2097,"imageUrl":"/data/news-images/251935.png"},{"title":"NurTureR High [v0.5.2] [DrBoki]","link":"https://f95zone.to/threads/nurturer-high-v0-5-2-drboki.256325/","threadId":256325,"pubDate":"2026-04-19T21:59:36.000Z","author":"7767","category":"Games","comments":624,"imageUrl":null},{"title":"Destined NTR [v0.1] [Eroshyl]","link":"https://f95zone.to/threads/destined-ntr-v0-1-eroshyl.284446/","threadId":284446,"pubDate":"2026-04-19T21:59:32.000Z","author":"eroshyl","category":"Games","comments":156,"imageUrl":"/data/news-images/284446.jpg"},{"title":"Taffy Tales [S2 Redux Demo] [UberPie]","link":"https://f95zone.to/threads/taffy-tales-s2-redux-demo-uberpie.9861/","threadId":9861,"pubDate":"2026-04-19T21:59:24.000Z","author":"Thrownaway13","category":"Games","comments":39085,"imageUrl":"/data/news-images/9861.jpg"},{"title":"Blacked House [v0.8] [Mandy]","link":"https://f95zone.to/threads/blacked-house-v0-8-mandy.227900/","threadId":227900,"pubDate":"2026-04-19T21:59:04.000Z","author":"mandystarrx","category":"Games","comments":760,"imageUrl":"/data/news-images/227900.png"},{"title":"Tokko Committee Ouka RPG-ZERO ( Ankoku Marimokan ) //  RJ01369348","link":"https://f95zone.to/threads/tokko-committee-ouka-rpg-zero-ankoku-marimokan-rj01369348.289260/","threadId":289260,"pubDate":"2026-04-19T21:58:25.000Z","author":"Gordon4321","category":"Request","comments":70,"imageUrl":null},{"title":"Hentai Rabbit Hood [2025-10-03] [DKT-DOKATA]","link":"https://f95zone.to/threads/hentai-rabbit-hood-2025-10-03-dkt-dokata.230893/","threadId":230893,"pubDate":"2026-04-19T21:58:16.000Z","author":"CrazedApple","category":"Games","comments":929,"imageUrl":null},{"title":"Minus8 ppppuXi [2020-07-31][PPPPU Modding Community]","link":"https://f95zone.to/threads/minus8-ppppuxi-2020-07-31-ppppu-modding-community.58056/","threadId":58056,"pubDate":"2026-04-19T21:58:10.000Z","author":"E N I G M A","category":"Mods","comments":1402,"imageUrl":"/data/news-images/58056.jpg"},{"title":"SiNiSistar 2 [v1.2.1] [Nennai 5]","link":"https://f95zone.to/threads/sinisistar-2-v1-2-1-nennai-5.112492/","threadId":112492,"pubDate":"2026-04-19T21:58:06.000Z","author":"BaasB","category":"Games","comments":8819,"imageUrl":"/data/news-images/112492.jpg"},{"title":"Twisted Memories [v0.9b] [BaiBai]","link":"https://f95zone.to/threads/twisted-memories-v0-9b-baibai.129520/","threadId":129520,"pubDate":"2026-04-19T21:58:04.000Z","author":"BaasB","category":"Games","comments":9124,"imageUrl":"/data/news-images/129520.jpg"},{"title":"The Adventurous Couple Original Story Gallery MOD [vS3P2dmab1] [asahibito]","link":"https://f95zone.to/threads/the-adventurous-couple-original-story-gallery-mod-vs3p2dmab1-asahibito.176215/","threadId":176215,"pubDate":"2026-04-19T21:58:00.000Z","author":"asahibito","category":"Mods","comments":59,"imageUrl":null},{"title":"Black Balance Collapse [Ch.3.64.92] [BlackBalance]","link":"https://f95zone.to/threads/black-balance-collapse-ch-3-64-92-blackbalance.277432/","threadId":277432,"pubDate":"2026-04-19T21:58:00.000Z","author":"Black Balance","category":"Games","comments":549,"imageUrl":"/data/news-images/277432.png"},{"title":"Pussy Fun [v2.7 Demo] [HH Richards]","link":"https://f95zone.to/threads/pussy-fun-v2-7-demo-hh-richards.152765/","threadId":152765,"pubDate":"2026-04-19T21:57:25.000Z","author":"hhrichards","category":"Games","comments":25,"imageUrl":"/data/news-images/152765.png"},{"title":"Ripples [v0.9.1] [Jestur]","link":"https://f95zone.to/threads/ripples-v0-9-1-jestur.56110/","threadId":56110,"pubDate":"2026-04-19T21:57:25.000Z","author":"7767","category":"Games","comments":17020,"imageUrl":null}]}