{"updated_at":"2026-04-13T02:00:13.504Z","count":20,"items":[{"title":"The Succubus Trap Island [Full Steam] [Tsukinomizu Project]","link":"https://f95zone.to/threads/the-succubus-trap-island-full-steam-tsukinomizu-project.88940/","threadId":88940,"pubDate":"2026-04-13T02:00:09.000Z","author":"C u n t","category":"Games","comments":311,"imageUrl":"/data/news-images/88940.jpg"},{"title":"[Translation Request] The Mask of Blue and Silver/蒼銀の仮面 [Nuko Majin]","link":"https://f95zone.to/threads/translation-request-the-mask-of-blue-and-silver-no-nuko-majin.228406/","threadId":228406,"pubDate":"2026-04-13T01:59:54.000Z","author":"Longhairlover010","category":"Request","comments":1318,"imageUrl":"/data/news-images/228406.jpg"},{"title":"(Translation request) Dragonlord's Ambition [Complete Edition]","link":"https://f95zone.to/threads/translation-request-dragonlords-ambition-complete-edition.43830/","threadId":43830,"pubDate":"2026-04-13T01:59:44.000Z","author":"Mirragez","category":"Request","comments":103,"imageUrl":null},{"title":"The Sunken Promise [v0.6] [NTRLORD]","link":"https://f95zone.to/threads/the-sunken-promise-v0-6-ntrlord.265997/","threadId":265997,"pubDate":"2026-04-13T01:59:23.000Z","author":"NTR_LORD","category":"Games","comments":1024,"imageUrl":"/data/news-images/265997.png"},{"title":"Big Brother Ultimate [v0.7] [WhiteSilver]","link":"https://f95zone.to/threads/big-brother-ultimate-v0-7-whitesilver.260017/","threadId":260017,"pubDate":"2026-04-13T01:59:09.000Z","author":"White Silver","category":"Games","comments":1922,"imageUrl":"/data/news-images/260017.png"},{"title":"NTR Phone [v0.39] [Shybox]","link":"https://f95zone.to/threads/ntr-phone-v0-39-shybox.211604/","threadId":211604,"pubDate":"2026-04-13T01:58:31.000Z","author":"Supreme_Evil","category":"Games","comments":2181,"imageUrl":"/data/news-images/211604.jpg"},{"title":"Hermione's Shop [v0.2.4] [KuroticaTeam]","link":"https://f95zone.to/threads/hermiones-shop-v0-2-4-kuroticateam.285434/","threadId":285434,"pubDate":"2026-04-13T01:58:17.000Z","author":"CluckKnight","category":"Games","comments":264,"imageUrl":"/data/news-images/285434.jpg"},{"title":"Artemis [v0.6.2b] [digi.B]","link":"https://f95zone.to/threads/artemis-v0-6-2b-digi-b.77680/","threadId":77680,"pubDate":"2026-04-13T01:58:13.000Z","author":"SilverLights","category":"Games","comments":12725,"imageUrl":"/data/news-images/77680.png"},{"title":"Heavy Five [Ch.2RS] [Nottravis]","link":"https://f95zone.to/threads/heavy-five-ch-2rs-nottravis.23184/","threadId":23184,"pubDate":"2026-04-13T01:58:09.000Z","author":"Nottravis","category":"Games","comments":26169,"imageUrl":null},{"title":"Nakara [v1.0.2] [Redspike]","link":"https://f95zone.to/threads/nakara-v1-0-2-redspike.182504/","threadId":182504,"pubDate":"2026-04-13T01:57:44.000Z","author":"Lykanter","category":"Games","comments":1363,"imageUrl":"/data/news-images/182504.jpg"},{"title":"MILFing Fields [v0.2.17] [Slutogen]","link":"https://f95zone.to/threads/milfing-fields-v0-2-17-slutogen.230569/","threadId":230569,"pubDate":"2026-04-13T01:57:28.000Z","author":"Slutogen Game Studio","category":"Games","comments":1158,"imageUrl":null},{"title":"Altered Bloodlines [v0.4] [Dream Cloud Entertainment]","link":"https://f95zone.to/threads/altered-bloodlines-v0-4-dream-cloud-entertainment.248001/","threadId":248001,"pubDate":"2026-04-13T01:57:09.000Z","author":"Lerd0","category":"Games","comments":118,"imageUrl":"/data/news-images/248001.png"},{"title":"Serenity [Ch. 2 v0.5] [N2TheFire]","link":"https://f95zone.to/threads/serenity-ch-2-v0-5-n2thefire.61604/","threadId":61604,"pubDate":"2026-04-13T01:56:39.000Z","author":"N2TheFire","category":"Games","comments":1926,"imageUrl":"/data/news-images/61604.png"},{"title":"Kingdom of Subversion [0.30.2] Legacy Memory Room v2 + Bug Fixes","link":"https://f95zone.to/threads/kingdom-of-subversion-0-30-2-legacy-memory-room-v2-bug-fixes.264168/","threadId":264168,"pubDate":"2026-04-13T01:56:37.000Z","author":"Tensa Zangetsu1000","category":"Mods","comments":27,"imageUrl":"/data/news-images/264168.png"},{"title":"NTR Mobile [v0.22.4] [NosyFellow]","link":"https://f95zone.to/threads/ntr-mobile-v0-22-4-nosyfellow.238597/","threadId":238597,"pubDate":"2026-04-13T01:56:32.000Z","author":"Lerd0","category":"Games","comments":7567,"imageUrl":null},{"title":"Unison corD [v1.06] [Hemoglobin A1C]","link":"https://f95zone.to/threads/unison-cord-v1-06-hemoglobin-a1c.293539/","threadId":293539,"pubDate":"2026-04-13T01:56:21.000Z","author":"SakuraKoi","category":"Games","comments":509,"imageUrl":"/data/news-images/293539.png"},{"title":"So Much to Love [0.2.8RP] [ALDOR]","link":"https://f95zone.to/threads/so-much-to-love-0-2-8rp-aldor.282192/","threadId":282192,"pubDate":"2026-04-13T01:55:44.000Z","author":"Aldor66","category":"Games","comments":677,"imageUrl":"/data/news-images/282192.png"},{"title":"Nothing Is Forever [v0.7.3] [MrSilverLust]","link":"https://f95zone.to/threads/nothing-is-forever-v0-7-3-mrsilverlust.87506/","threadId":87506,"pubDate":"2026-04-13T01:55:35.000Z","author":"MrSilverLust","category":"Games","comments":4664,"imageUrl":"/data/news-images/87506.jpg"},{"title":"The Villain Simulator [Beta v48a] [ZnelArts]","link":"https://f95zone.to/threads/the-villain-simulator-beta-v48a-znelarts.7252/","threadId":7252,"pubDate":"2026-04-13T01:55:26.000Z","author":"Twistty","category":"Games","comments":4035,"imageUrl":"/data/news-images/7252.jpg"},{"title":"Insatiable [P2 v0.0.4] [cumAgain? Games]","link":"https://f95zone.to/threads/insatiable-p2-v0-0-4-cumagain-games.115405/","threadId":115405,"pubDate":"2026-04-13T01:55:06.000Z","author":"BaasB","category":"Games","comments":992,"imageUrl":"/data/news-images/115405.png"}]}