{"updated_at":"2026-03-23T05:00:12.576Z","count":20,"items":[{"title":"Nymphomania Priestess [v0.8g] [TechnoBrake]","link":"https://f95zone.to/threads/nymphomania-priestess-v0-8g-technobrake.44110/","threadId":44110,"pubDate":"2026-03-23T05:00:01.000Z","author":"BabyYoda","category":"Games","comments":26028,"imageUrl":"/data/news-images/44110.png"},{"title":"Shadows of Desire [v0.8.5] [Shamantr]","link":"https://f95zone.to/threads/shadows-of-desire-v0-8-5-shamantr.171123/","threadId":171123,"pubDate":"2026-03-23T04:59:39.000Z","author":"7767","category":"Games","comments":7394,"imageUrl":"/data/news-images/171123.png"},{"title":"Make Me Famous [Ch.4 P1] [StanLock]","link":"https://f95zone.to/threads/make-me-famous-ch-4-p1-stanlock.271944/","threadId":271944,"pubDate":"2026-03-23T04:59:30.000Z","author":"StanLock","category":"Games","comments":169,"imageUrl":"/data/news-images/271944.png"},{"title":"A Mother's Love [Part 1-16 Plus] [OrbOrigin]","link":"https://f95zone.to/threads/a-mothers-love-part-1-16-plus-orborigin.25146/","threadId":25146,"pubDate":"2026-03-23T04:59:02.000Z","author":"UncleVT","category":"Games","comments":14415,"imageUrl":null},{"title":"The Manor: Whispers of Lust [v0.1b] [Dr. Lustwell]","link":"https://f95zone.to/threads/the-manor-whispers-of-lust-v0-1b-dr-lustwell.277190/","threadId":277190,"pubDate":"2026-03-23T04:59:01.000Z","author":"Dr. Lustwell","category":"Games","comments":254,"imageUrl":"/data/news-images/277190.png"},{"title":"The Sex Teacher [S01 Ep 02] [The Sex Teacher]","link":"https://f95zone.to/threads/the-sex-teacher-s01-ep-02-the-sex-teacher.289561/","threadId":289561,"pubDate":"2026-03-23T04:58:51.000Z","author":"Æяiк","category":"Games","comments":53,"imageUrl":null},{"title":"Harvesting Corruption [v0.0.22] [Nuverotic]","link":"https://f95zone.to/threads/harvesting-corruption-v0-0-22-nuverotic.244811/","threadId":244811,"pubDate":"2026-03-23T04:58:50.000Z","author":"7767","category":"Games","comments":1254,"imageUrl":"/data/news-images/244811.gif"},{"title":"A Wife and Mother [P2 v0.230a + P1 v0.152] [Lust &amp; Passion]","link":"https://f95zone.to/threads/a-wife-and-mother-p2-v0-230a-p1-v0-152-lust-passion.5944/","threadId":5944,"pubDate":"2026-03-23T04:58:46.000Z","author":"CobraSGT","category":"Games","comments":178614,"imageUrl":"/data/news-images/5944.jpg"},{"title":"Mind Control: Twisted Thoughts [v0.26 Beta] [specialmind]","link":"https://f95zone.to/threads/mind-control-twisted-thoughts-v0-26-beta-specialmind.188539/","threadId":188539,"pubDate":"2026-03-23T04:58:34.000Z","author":"mindcontroldev","category":"Games","comments":1609,"imageUrl":"/data/news-images/188539.jpg"},{"title":"Master of Seduction [v0.20.0] [HexorGames]","link":"https://f95zone.to/threads/master-of-seduction-v0-20-0-hexorgames.159738/","threadId":159738,"pubDate":"2026-03-23T04:58:26.000Z","author":"HexorGames","category":"Games","comments":1228,"imageUrl":"/data/news-images/159738.jpg"},{"title":"Paths [R16] [Stratos]","link":"https://f95zone.to/threads/paths-r16-stratos.47766/","threadId":47766,"pubDate":"2026-03-23T04:57:58.000Z","author":"StratosDBG","category":"Games","comments":488,"imageUrl":"/data/news-images/47766.png"},{"title":"Law School [S2 Ep.4 v4] [MisterMaya]","link":"https://f95zone.to/threads/law-school-s2-ep-4-v4-mistermaya.184252/","threadId":184252,"pubDate":"2026-03-23T04:57:50.000Z","author":"MisterMaya","category":"Games","comments":8487,"imageUrl":"/data/news-images/184252.png"},{"title":"NamelessXIII Collection [2024-03-14] [XIIINameless]","link":"https://f95zone.to/threads/namelessxiii-collection-2024-03-14-xiiinameless.199547/","threadId":199547,"pubDate":"2026-03-23T04:57:45.000Z","author":"HeavyLead","category":"Animations & Loops","comments":85,"imageUrl":"/data/news-images/199547.gif"},{"title":"Back Again [Rework v0.14] [BigBoy Projects]","link":"https://f95zone.to/threads/back-again-rework-v0-14-bigboy-projects.191460/","threadId":191460,"pubDate":"2026-03-23T04:57:39.000Z","author":"UncleVT","category":"Games","comments":1439,"imageUrl":"/data/news-images/191460.png"},{"title":"Sexting Department [v0.0.9] [SextingDepartment]","link":"https://f95zone.to/threads/sexting-department-v0-0-9-sextingdepartment.270231/","threadId":270231,"pubDate":"2026-03-23T04:55:31.000Z","author":"SextingDepartment","category":"Games","comments":625,"imageUrl":"/data/news-images/270231.png"},{"title":"Long Road Home [Ep.16] [OBDGames]","link":"https://f95zone.to/threads/long-road-home-ep-16-obdgames.45466/","threadId":45466,"pubDate":"2026-03-23T04:55:13.000Z","author":"Crazygamer43","category":"Games","comments":22284,"imageUrl":"/data/news-images/45466.png"},{"title":"Knight of Love [1K1] [Slightly Pink Heart]","link":"https://f95zone.to/threads/knight-of-love-1k1-slightly-pink-heart.48363/","threadId":48363,"pubDate":"2026-03-23T04:55:01.000Z","author":"SlightlyPinkHeart","category":"Games","comments":3147,"imageUrl":"/data/news-images/48363.png"},{"title":"Honey Select 2 [DX R16] [Illusion]","link":"https://f95zone.to/threads/honey-select-2-dx-r16-illusion.53457/","threadId":53457,"pubDate":"2026-03-23T04:54:57.000Z","author":"Ryahn's Slut","category":"Games","comments":20963,"imageUrl":"/data/news-images/53457.jpg"},{"title":"Stuck at Home [v0.4.0b] [Moraion]","link":"https://f95zone.to/threads/stuck-at-home-v0-4-0b-moraion.101334/","threadId":101334,"pubDate":"2026-03-23T04:54:39.000Z","author":"BaasB","category":"Games","comments":2018,"imageUrl":"/data/news-images/101334.png"},{"title":"Domino Beach [Ep.3 Full] [Mr Jet]","link":"https://f95zone.to/threads/domino-beach-ep-3-full-mr-jet.214365/","threadId":214365,"pubDate":"2026-03-23T04:54:05.000Z","author":"BaasB","category":"Games","comments":1837,"imageUrl":"/data/news-images/214365.png"}]}