{"updated_at":"2026-03-27T20:15:13.847Z","count":20,"items":[{"title":"Magical Girl Luna's Misfortunes [v1.09] [namaste koboo]","link":"https://f95zone.to/threads/magical-girl-lunas-misfortunes-v1-09-namaste-koboo.219616/","threadId":219616,"pubDate":"2026-03-27T20:15:06.000Z","author":"Supreme_Evil","category":"Games","comments":175,"imageUrl":"/data/news-images/219616.png"},{"title":"Corrupted Seas [v0.5b] [bluebite]","link":"https://f95zone.to/threads/corrupted-seas-v0-5b-bluebite.190556/","threadId":190556,"pubDate":"2026-03-27T20:14:55.000Z","author":"Deleted member 4940590","category":"Games","comments":437,"imageUrl":null},{"title":"Living Your Futanari Fantasy: Granted [Development Thread] - FUTA ON MALE VN","link":"https://f95zone.to/threads/living-your-futanari-fantasy-granted-development-thread-futa-on-male-vn.288412/","threadId":288412,"pubDate":"2026-03-27T20:14:53.000Z","author":"tiltproofno","category":"Programming, Development & Art","comments":154,"imageUrl":"/data/news-images/288412.jpg"},{"title":"Monster Black Market [v2.1.1.0DLC] [Team-Apple Pie]","link":"https://f95zone.to/threads/monster-black-market-v2-1-1-0dlc-team-apple-pie.124772/","threadId":124772,"pubDate":"2026-03-27T20:14:51.000Z","author":"BaasB","category":"Games","comments":10519,"imageUrl":"/data/news-images/124772.png"},{"title":"WVM [S2 Ch.1 Ep.13 F] [Braindrop]","link":"https://f95zone.to/threads/wvm-s2-ch-1-ep-13-f-braindrop.35910/","threadId":35910,"pubDate":"2026-03-27T20:14:48.000Z","author":"7767","category":"Games","comments":77015,"imageUrl":"/data/news-images/35910.png"},{"title":"Lunar's Chosen [Ep.2 v0.8 Public] [PTGames]","link":"https://f95zone.to/threads/lunars-chosen-ep-2-v0-8-public-ptgames.28364/","threadId":28364,"pubDate":"2026-03-27T20:14:34.000Z","author":"TheImage","category":"Games","comments":8153,"imageUrl":"/data/news-images/28364.png"},{"title":"Carnal Instinct [v0.7.5] [Team Carnal Instinct]","link":"https://f95zone.to/threads/carnal-instinct-v0-7-5-team-carnal-instinct.65211/","threadId":65211,"pubDate":"2026-03-27T20:14:26.000Z","author":"BaasB","category":"Games","comments":9690,"imageUrl":"/data/news-images/65211.jpg"},{"title":"Heartbeat Casino-Hotel [Ch.1] [Monobloc]","link":"https://f95zone.to/threads/heartbeat-casino-hotel-ch-1-monobloc.292596/","threadId":292596,"pubDate":"2026-03-27T20:14:22.000Z","author":"BaasB","category":"Games","comments":6,"imageUrl":"/data/news-images/292596.png"},{"title":"LISTA DE JUEGOS EN ESPAÑOL/SPANISH GAMES","link":"https://f95zone.to/threads/lista-de-juegos-en-espanol-spanish-games.31851/","threadId":31851,"pubDate":"2026-03-27T20:14:20.000Z","author":"MATY76","category":"Translation","comments":54301,"imageUrl":null},{"title":"Futaisekai - A Tale of Unintended Fate [v0.26] [Futa Isekai]","link":"https://f95zone.to/threads/futaisekai-a-tale-of-unintended-fate-v0-26-futa-isekai.165547/","threadId":165547,"pubDate":"2026-03-27T20:14:00.000Z","author":"BaasB","category":"Games","comments":1399,"imageUrl":"/data/news-images/165547.jpg"},{"title":"Race of Life [Act 2 Ep.4 Fix 4] [Underground Studio]","link":"https://f95zone.to/threads/race-of-life-act-2-ep-4-fix-4-underground-studio.130096/","threadId":130096,"pubDate":"2026-03-27T20:13:44.000Z","author":"UndergroundStudio","category":"Games","comments":11336,"imageUrl":"/data/news-images/130096.png"},{"title":"Cosy Cafe [v0.13.1 Public] [Cosy Creator]","link":"https://f95zone.to/threads/cosy-cafe-v0-13-1-public-cosy-creator.143711/","threadId":143711,"pubDate":"2026-03-27T20:13:21.000Z","author":"Cosy Creator","category":"Games","comments":9066,"imageUrl":"/data/news-images/143711.jpg"},{"title":"Summer's Gone [S1 Steam + DLC] [Oceanlab]","link":"https://f95zone.to/threads/summers-gone-s1-steam-dlc-oceanlab.29981/","threadId":29981,"pubDate":"2026-03-27T20:13:08.000Z","author":"7767","category":"Games","comments":54609,"imageUrl":"/data/news-images/29981.png"},{"title":"StickySpoodge Collection [2026-03-02] [StickySp00dge/Stickyspud]","link":"https://f95zone.to/threads/stickyspoodge-collection-2026-03-02-stickysp00dge-stickyspud.220324/","threadId":220324,"pubDate":"2026-03-27T20:13:07.000Z","author":"Kosumo Aphrodisia","category":"Animations & Loops","comments":887,"imageUrl":null},{"title":"CelSector [v1.1.1] [YumamiSoft]","link":"https://f95zone.to/threads/celsector-v1-1-1-yumamisoft.283889/","threadId":283889,"pubDate":"2026-03-27T20:12:51.000Z","author":"Bob69","category":"Games","comments":1917,"imageUrl":"/data/news-images/283889.png"},{"title":"Babysitting Cream: BetaMix Edition [v0.3.5] [Novilon]","link":"https://f95zone.to/threads/babysitting-cream-betamix-edition-v0-3-5-novilon.113170/","threadId":113170,"pubDate":"2026-03-27T20:12:50.000Z","author":"Novilon","category":"Games","comments":3362,"imageUrl":"/data/news-images/113170.jpg"},{"title":"FreshWomen [Season 3 - 10%] [OppaiMan]","link":"https://f95zone.to/threads/freshwomen-season-3-10-oppaiman.79740/","threadId":79740,"pubDate":"2026-03-27T20:12:37.000Z","author":"7767","category":"Games","comments":7517,"imageUrl":"/data/news-images/79740.png"},{"title":"Katalist [v0.098.2] [Tearycian]","link":"https://f95zone.to/threads/katalist-v0-098-2-tearycian.53384/","threadId":53384,"pubDate":"2026-03-27T20:12:32.000Z","author":"Tearycian","category":"Games","comments":12012,"imageUrl":"/data/news-images/53384.png"},{"title":"Boutoku no Seijo Natalia: Kon’yakusha no Noroi o Toku tame ni Mizukara Netorareru Shoujo no Mokushiroku 冒涜の聖女ナタリア～婚約者の呪いを解くために自ら寝取られる少女の黙示録～ RJ0153343","link":"https://f95zone.to/threads/boutoku-no-seijo-natalia-konyakusha-no-noroi-o-toku-tame-ni-mizukara-netorareru-shoujo-no-mokushiroku-no-nataria-no-iwo-kutameni-ra-rareru-no-rj0153343.291611/","threadId":291611,"pubDate":"2026-03-27T20:12:28.000Z","author":"stupid_army","category":"Request","comments":56,"imageUrl":"/data/news-images/291611.jpg"},{"title":"Nothing Weird Happens Here [v0.51] [Owl34Games]","link":"https://f95zone.to/threads/nothing-weird-happens-here-v0-51-owl34games.288066/","threadId":288066,"pubDate":"2026-03-27T20:12:26.000Z","author":"Owl34Games","category":"Games","comments":217,"imageUrl":"/data/news-images/288066.png"}]}