{"updated_at":"2026-04-08T14:30:12.936Z","count":20,"items":[{"title":"Problematic Subjects [v1.2.0] [Babus Games]","link":"https://f95zone.to/threads/problematic-subjects-v1-2-0-babus-games.265496/","threadId":265496,"pubDate":"2026-04-08T14:29:58.000Z","author":"BaasB","category":"Games","comments":758,"imageUrl":null},{"title":"NTR Fates: Anamnesis [v0.4.8] [Mystichef]","link":"https://f95zone.to/threads/ntr-fates-anamnesis-v0-4-8-mystichef.258512/","threadId":258512,"pubDate":"2026-04-08T14:29:58.000Z","author":"Mystichef","category":"Games","comments":787,"imageUrl":"/data/news-images/258512.png"},{"title":"A Simple Life with My Unobtrusive Sister [v1.02 rev1] [Countercurrent Tea Party]","link":"https://f95zone.to/threads/a-simple-life-with-my-unobtrusive-sister-v1-02-rev1-countercurrent-tea-party.221086/","threadId":221086,"pubDate":"2026-04-08T14:29:44.000Z","author":"BaasB","category":"Games","comments":5602,"imageUrl":null},{"title":"Ubbak's Mod for My Girlfriend Advanced to the Dancer Class [V2.11] [Ubbak]","link":"https://f95zone.to/threads/ubbaks-mod-for-my-girlfriend-advanced-to-the-dancer-class-v2-11-ubbak.293473/","threadId":293473,"pubDate":"2026-04-08T14:29:38.000Z","author":"Ubbak","category":"Mods","comments":44,"imageUrl":null},{"title":"Honey Select 2 [DX R16] [Illusion]","link":"https://f95zone.to/threads/honey-select-2-dx-r16-illusion.53457/","threadId":53457,"pubDate":"2026-04-08T14:29:20.000Z","author":"Ryahn's Slut","category":"Games","comments":21293,"imageUrl":"/data/news-images/53457.jpg"},{"title":"My Girlfriend's New Kink [v0.7 Public] [Omega Games]","link":"https://f95zone.to/threads/my-girlfriends-new-kink-v0-7-public-omega-games.241921/","threadId":241921,"pubDate":"2026-04-08T14:29:18.000Z","author":"Omega Games","category":"Games","comments":1305,"imageUrl":"/data/news-images/241921.gif"},{"title":"Temptation District [Preview] [Guz]","link":"https://f95zone.to/threads/temptation-district-preview-guz.293204/","threadId":293204,"pubDate":"2026-04-08T14:29:13.000Z","author":"guz_tv","category":"Games","comments":21,"imageUrl":"/data/news-images/293204.jpg"},{"title":"The Wreck of the Spaceship Todoroki [v1.03] [natyusyo]","link":"https://f95zone.to/threads/the-wreck-of-the-spaceship-todoroki-v1-03-natyusyo.104874/","threadId":104874,"pubDate":"2026-04-08T14:29:06.000Z","author":"Crazygamer43","category":"Games","comments":610,"imageUrl":"/data/news-images/104874.jpg"},{"title":"The Last Embrace [v0.3.5 Demo] [NoX Productions]","link":"https://f95zone.to/threads/the-last-embrace-v0-3-5-demo-nox-productions.266779/","threadId":266779,"pubDate":"2026-04-08T14:28:58.000Z","author":"Bob69","category":"Games","comments":353,"imageUrl":"/data/news-images/266779.png"},{"title":"Friends in Need [Ch.14 Test] [NeonGhosts]","link":"https://f95zone.to/threads/friends-in-need-ch-14-test-neonghosts.112500/","threadId":112500,"pubDate":"2026-04-08T14:28:55.000Z","author":"NeonGhosts","category":"Games","comments":25772,"imageUrl":"/data/news-images/112500.png"},{"title":"Little Sister: New Era [v0.09] [Master Wuju]","link":"https://f95zone.to/threads/little-sister-new-era-v0-09-master-wuju.213088/","threadId":213088,"pubDate":"2026-04-08T14:28:51.000Z","author":"Bob69","category":"Games","comments":157,"imageUrl":"/data/news-images/213088.jpg"},{"title":"Shadows of Ambition [Ch.7.1] [AbyssGames]","link":"https://f95zone.to/threads/shadows-of-ambition-ch-7-1-abyssgames.231321/","threadId":231321,"pubDate":"2026-04-08T14:28:48.000Z","author":"7767","category":"Games","comments":3974,"imageUrl":"/data/news-images/231321.png"},{"title":"netori (?) games","link":"https://f95zone.to/threads/netori-games.20817/","threadId":20817,"pubDate":"2026-04-08T14:28:39.000Z","author":"skazy","category":"Recommendations & Identification","comments":1126,"imageUrl":null},{"title":"The Golden Boy [v0.7 Producer Version] [Serious Punch]","link":"https://f95zone.to/threads/the-golden-boy-v0-7-producer-version-serious-punch.142777/","threadId":142777,"pubDate":"2026-04-08T14:28:32.000Z","author":"Serious Punch","category":"Games","comments":2424,"imageUrl":"/data/news-images/142777.png"},{"title":"Waifu Academy [v0.13.5] [Irphaeus]","link":"https://f95zone.to/threads/waifu-academy-v0-13-5-irphaeus.9414/","threadId":9414,"pubDate":"2026-04-08T14:28:31.000Z","author":"Charolastra","category":"Games","comments":26839,"imageUrl":"/data/news-images/9414.png"},{"title":"Unison corD [v1.06] [Hemoglobin A1C]","link":"https://f95zone.to/threads/unison-cord-v1-06-hemoglobin-a1c.293539/","threadId":293539,"pubDate":"2026-04-08T14:28:30.000Z","author":"SakuraKoi","category":"Games","comments":192,"imageUrl":"/data/news-images/293539.png"},{"title":"Western Sharing Games List","link":"https://f95zone.to/threads/western-sharing-games-list.226259/","threadId":226259,"pubDate":"2026-04-08T14:28:22.000Z","author":"Pr0GamerJohnny","category":"Recommendations & Identification","comments":5080,"imageUrl":null},{"title":"NTR Sim [v0.3.1] [KTRGames]","link":"https://f95zone.to/threads/ntr-sim-v0-3-1-ktrgames.290010/","threadId":290010,"pubDate":"2026-04-08T14:28:21.000Z","author":"Kurotori","category":"Games","comments":326,"imageUrl":null},{"title":"Chasing Soul [v0.1] [illudev]","link":"https://f95zone.to/threads/chasing-soul-v0-1-illudev.291697/","threadId":291697,"pubDate":"2026-04-08T14:28:21.000Z","author":"illudev","category":"Games","comments":56,"imageUrl":null},{"title":"Mario Is Missing - Peach's Untold Tale [v3.48] [Ivan Aedler]","link":"https://f95zone.to/threads/mario-is-missing-peachs-untold-tale-v3-48-ivan-aedler.137/","threadId":137,"pubDate":"2026-04-08T14:28:18.000Z","author":"7767","category":"Games","comments":803,"imageUrl":"/data/news-images/137.png"}]}